[
{
    "id": "60056333",
    "login": "tfue"
},
{
    "id": "55125740",
    "login": "fortnite"
},
{
    "id": "39298218",
    "login": "dakotaz"
},
{
    "id": "15564828",
    "login": "nickmercs"
},
{
    "id": "36769016",
    "login": "timthetatman"
},
{
    "id": "127651530",
    "login": "tsm_daequan"
},
{
    "id": "110690086",
    "login": "tsm_myth"
},
{
    "id": "84752541",
    "login": "highdistortion"
},
{
    "id": "32140000",
    "login": "sypherpk"
},
{
    "id": "67143805",
    "login": "tsm_hamlinz"
},
{
    "id": "14408894",
    "login": "cdnthe3rd"
},
{
    "id": "29829912",
    "login": "drlupo"
},
{
    "id": "128489946",
    "login": "cizzorz"
},
{
    "id": "66691674",
    "login": "kingrichard"
},
{
    "id": "44445592",
    "login": "pokimane"
},
{
    "id": "106125347",
    "login": "couragejd"
},
{
    "id": "81687332",
    "login": "cloakzy"
},
{
    "id": "74352492",
    "login": "vivid"
},
{
    "id": "79615025",
    "login": "valkyrae"
},
{
    "id": "172044925",
    "login": "skysparrowstorm"
}]
